analytics_command_center/__init__.py
analytics_command_center/launcher.py
analytics_command_center/auth/__init__.py
analytics_command_center/auth/auth_model.py
analytics_command_center/auth/auth_service_bloc.py
analytics_command_center/auth/auth_service_model.py
analytics_command_center/auth/auth_service_provider.py
analytics_command_center/common/__init__.py
analytics_command_center/common/huemul_common.py
analytics_command_center/common/huemul_connection.py
analytics_command_center/common/huemul_datetime_part.py
analytics_command_center/common/huemul_error.py
analytics_command_center/common/huemul_functions.py
analytics_command_center/common/huemul_http_info.py
analytics_command_center/common/huemul_logging.py
analytics_command_center/common/huemul_param.py
analytics_command_center/common/huemul_response_bloc.py
analytics_command_center/common/huemul_response_error.py
analytics_command_center/common/huemul_response_provider.py
analytics_command_center/modules/__init__.py
analytics_command_center/modules/process_exec/__init__.py
analytics_command_center/modules/process_exec/process_exec_bloc.py
analytics_command_center/modules/process_exec/process_exec_provider.py
analytics_command_center/modules/process_exec/process_exec_response_model.py
analytics_command_center/modules/process_exec/process_exec_start_model.py
analytics_command_center/modules/process_exec/process_exec_stop_model.py
analytics_command_center/modules/process_exec_global_path/__init__.py
analytics_command_center/modules/process_exec_global_path/process_exec_global_path_bloc.py
analytics_command_center/modules/process_exec_global_path/process_exec_global_path_model.py
analytics_command_center/modules/process_exec_global_path/process_exec_global_path_provider.py
analytics_command_center/modules/process_exec_param/__init__.py
analytics_command_center/modules/process_exec_param/process_exec_param_model.py
analytics_command_center/modules/process_exec_raw_file/__init__.py
analytics_command_center-3.0.14.dist-info/LICENSE
analytics_command_center-3.0.14.dist-info/METADATA
analytics_command_center-3.0.14.dist-info/WHEEL
analytics_command_center-3.0.14.dist-info/top_level.txt
analytics_command_center-3.0.14.dist-info/RECORD
