Metadata-Version: 2.1
Name: analytics-command-center
Version: 3.0.14
Summary: Command Center for Data Ingestion, Advanced Analytics and Artificial Intelligence process
Home-page: https://analytics-command-center.com
Author: Developer Code HuemulSolutions
Author-email: developer.code@huemulsolutions.com
License: UNKNOWN
Project-URL: Bug Tracker, https://github.com/HuemulSolutions/huemul-bigdatagovernance/issues
Platform: UNKNOWN
Classifier: Programming Language :: Python :: 3
Classifier: License :: OSI Approved :: MIT License
Classifier: Operating System :: OS Independent
Requires-Python: >=3.6
License-File: LICENSE
